child/__init__.py
child/child_file.py
code_package-1.0.2.dist-info/METADATA
code_package-1.0.2.dist-info/WHEEL
code_package-1.0.2.dist-info/top_level.txt
code_package-1.0.2.dist-info/RECORD
