Metadata-Version: 2.1
Name: code-package
Version: 1.0.2
Summary: You dont want this package
Home-page: https://go_somewhere_else.com
Author: bg
Author-email: bg@gb.com
License: UNKNOWN
Platform: UNKNOWN
Requires-Dist: numpy
